{
    "34.147.120.111": {
        "80": {
            "Hostname": "",
            "Protocol": "tcp",
            "State": "filtered",
            "Service": "http",
            "Product": "",
            "Version": "",
            "Vulners": "",
            "Web Source": "Error: No se pudo obtener el codigo fuente",
            "Screenshot": "results/Marca/2023-03-24_marca.com/img/34.147.120.111_80.png"
        },
        "443": {
            "Hostname": "",
            "Protocol": "tcp",
            "State": "filtered",
            "Service": "https",
            "Product": "",
            "Version": "",
            "Vulners": "",
            "Web Source": "Error: No se pudo conectar al servicio web",
            "Screenshot": "results/Marca/2023-03-24_marca.com/img/34.147.120.111_443.png"
        }
    }
}